data_enum/__init__.py
tests/__init__.py
tests/test_data_enum.py
data_enum-2.0.1.dist-info/LICENSE
data_enum-2.0.1.dist-info/METADATA
data_enum-2.0.1.dist-info/WHEEL
data_enum-2.0.1.dist-info/top_level.txt
data_enum-2.0.1.dist-info/RECORD
