Metadata-Version: 2.1
Name: data-enum
Version: 2.0.1
Summary: An alternative to the built-in Python `enum` implementation
Home-page: https://github.com/chasefinch/data-enum
Author: Chase Finch
Author-email: chase@finch.email
License: UNKNOWN
Keywords: Enum,Enumeration
Platform: UNKNOWN
Classifier: Programming Language :: Python :: 3
Classifier: Programming Language :: Python :: 3.6
Classifier: Programming Language :: Python :: 3.7
Classifier: Programming Language :: Python :: 3.8
Classifier: Programming Language :: Python :: 3.9
Classifier: License :: OSI Approved :: Apache Software License
Classifier: Operating System :: OS Independent
Requires-Python: >=3.6
License-File: LICENSE
